{
  "id": "hiresphere-local-example",
  "name": "HireSphere Local Example",
  "values": [
    { "key": "baseUrl", "value": "http://localhost:5167/api", "enabled": true },
    { "key": "accessToken", "value": "", "enabled": true },
    { "key": "candidateEmail", "value": "REPLACE_CANDIDATE_EMAIL", "enabled": true },
    { "key": "candidatePassword", "value": "REPLACE_CANDIDATE_PASSWORD", "enabled": true },
    { "key": "recruiterEmail", "value": "REPLACE_RECRUITER_EMAIL", "enabled": true },
    { "key": "recruiterPassword", "value": "REPLACE_RECRUITER_PASSWORD", "enabled": true },
    { "key": "managerEmail", "value": "REPLACE_MANAGER_EMAIL", "enabled": true },
    { "key": "managerPassword", "value": "REPLACE_MANAGER_PASSWORD", "enabled": true },
    { "key": "adminEmail", "value": "REPLACE_ADMIN_EMAIL", "enabled": true },
    { "key": "adminPassword", "value": "REPLACE_ADMIN_PASSWORD", "enabled": true },
    { "key": "jobId", "value": "0", "enabled": true },
    { "key": "applicationId", "value": "0", "enabled": true }
  ],
  "_postman_variable_scope": "environment"
}
